ikalogic/__init__.py
ikalogic/sp1000g/__init__.py
ikalogic/sp1000g/_sp1000g_py.cpython-312-x86_64-linux-gnu.so
ikalogic/sp1000g/libftd3xx.so
ikalogic/sp1000g/libsp1000g_api.so
ikalogic/sp1000g/libsp1000g_api.so.1
ikalogic/sp1000g/libsp1000g_api.so.1.0
ikalogic/sp1000g/libsp1000g_api.so.1.0.0
ikalogic_sp1000g-0.1.13.dist-info/METADATA
ikalogic_sp1000g-0.1.13.dist-info/WHEEL
ikalogic_sp1000g-0.1.13.dist-info/top_level.txt
ikalogic_sp1000g-0.1.13.dist-info/RECORD
