Metadata-Version: 2.4
Name: ikalogic-sp1000g
Version: 0.1.13
Summary: Python bindings for SP1000G Logic Analyzer API
Home-page: https://ikalogic.com
Author: Ikalogic
Author-email: Ikalogic <support@ikalogic.com>
License: MIT
Keywords: logic analyzer,hardware,sp1000g,ikalogic
Classifier: Development Status :: 4 - Beta
Classifier: Intended Audience :: Developers
Classifier: Topic :: Software Development :: Libraries
Classifier: Topic :: System :: Hardware
Classifier: License :: OSI Approved :: MIT License
Classifier: Programming Language :: Python :: 3
Classifier: Programming Language :: Python :: 3.7
Classifier: Programming Language :: Python :: 3.8
Classifier: Programming Language :: Python :: 3.9
Classifier: Programming Language :: Python :: 3.10
Classifier: Programming Language :: Python :: 3.11
Classifier: Programming Language :: Python :: 3.12
Classifier: Operating System :: POSIX :: Linux
Classifier: Environment :: Console
Requires-Python: >=3.7
Requires-Dist: pybind11>=2.10.0
Dynamic: author
Dynamic: home-page
Dynamic: requires-python
